{
  "book": "osee",
  "book_title": "The Prophecy of Osee.",
  "short_title": "Osee",
  "hebrew_title": null,
  "intros": [
    {
      "title": "THE PROPHECY OF OSEE.",
      "text": "<i>OSEE</i> born <i>in Belomoth</i> (as writeth S. Epiphanius) <i>of the tribe of Issachar</i>, prophesied <i>in the</i> <mn>[1]</mn> <mn>[2]</mn> <i>reign of Ozias</i> (otherwise called Azarias) <i>Joathan, Achaz, Ezechias</i>, Kings of Juda, and of <i>Jeroboam</i> the son of Joas King of Israel; and of the residue of the Kings of Israel, even to their captivity, which happened in the sixth year of Ezechias King of Juda. This Prophet <i>taking</i> by God's commandment <i>a fornicatrix to wife, and having children that became also fornicators</i>, by these figures, and by <i>a widow long expecting another husband</i>, and the like parables, and other preaching, admonisheth both the Kingdoms of Israel and Juda, that for their obstinacy in sins, they shall fall, first the one and afterwards the other, into miserable captivity. Exhorteth them to repentance; <mn>[3]</mn> foresheweth their release; and the coming of Christ our Redeemer, with aboundance of grace, <mn>[4]</mn> and benefits to all nations.",
      "default": true,
      "notes": [
        {
          "marker": 1,
          "text": "Osee of the tribe of Issachar prophesieth the captivity of both Kingdoms."
        },
        {
          "marker": 2,
          "text": "<i>De vita & interitu prophetar. 4. Reg. 17. S. Iero. Ep. ad Paulin.</i>"
        },
        {
          "marker": 3,
          "text": "Their relaxation."
        },
        {
          "marker": 4,
          "text": "And coming of Christ. (b)"
        }
      ]
    },
    {
      "title": "THE ARGUMENT OF THE TWELVE LESS PROPHECIES.",
      "text": "<i>WHY Isai, Jeremie, Ezechiel</i>, and <i>Daniel</i> are called the four greater Prophets, & these twelve <mn>[1]</mn> <mn>[2]</mn> the less, there seemeth no other certain and proper reason, but because they writ more largely, and these more briefly. For otherwise without essential difference, all the sixteen, as also Baruch (whose Book is inserted with Jeremie's) and Moyses, Samuel, the Royal Psalmist David, Nathan, Elias, Elizeus, Esdras, Nehemias, & many others, some writing Books, some not, were absolutely true Prophets of God, endued with the holy spirit of prophecy; had the like revelations, with <mn>[3]</mn> the same assurance of truth, in great part of the same Mysteries, as well pertaining to the old Testament, as to the New. And so these twelve, <i>contracted into the straitness of one volume</i> (saith S. Jerom.) multo aliud, quam sonant in litera, praefigurant: <i>Prefigurate a far other thing, than they</i> <mn>[4]</mn> <i>sound in the letter</i>. Signifying, as he elsewhere explicateth, that they do foreshew many <mn>[5]</mn> important things, not only pertaining to the Jews, and some other peoples of those former times, but also of all nations to be converted to Christ. They were not all at one time: but <i>Osee, Ioel,</i> <mn>[6]</mn> <i>Amos, Abdias, Jonas</i>, & <i>Micheas</i>, prophesied before the captivity of the ten Tribes. <i>Nahum,</i> <mn>[7]</mn> <i>Habacuc</i>, & <i>Sophonias</i>, after that captivity, & before the captivity of the two Tribes. And the other three <i>Aggaeus, Zacharias</i>, and <i>Malachie</i>, after the relaxation from captivity. Neither did they all prophesy in the same places: nor concerning the same people; and so have their particular arguments, as we shall briefly note of every one, as they follow in order.\n\nHere we may note for instruction of the vulgar reader, that the Prophets commonly use one of these names, when they direct their speech of the <mn>◦</mn>\n\n\n\nBecause <i>Juda</i> was the chief, and most worthy tribe. <i>Benjamin</i> the other only tribe (besides Levi) that joined with Juda. <i>Jerusalem</i> the Metropolitan & Royal city, where both the Temple, and King's palace were situated. <i>The House of David</i> is the family, whereof succeeded all the Kings of that Kingdom, so long as it stood; and of which some remained in more estimation than any other even to Christ.\nLikewise they use some of these other names, when they speak of the <mn>◦</mn>\n\n\n\nFor that their first King Jeroboam was of the tribe of <i>Ephraim</i>, and so descended from <i>Joseph; Samaria</i>, and <i>Jezrahel</i> were the chiefest cities of that Kingdom; <i>Bethel</i> was one of the places (Dan the other) where Jeroboam set up the two calves. Which place was otherwise, and more truly called <i>Bethaven</i>, the house of the idol, or of vanity, or iniquity. The names also of <i>Israel</i> and <i>Jacob</i>, <mn>◦</mn> were more commonly used for the ten tribes; who being more in number, usurped and appropriated to themselves the names of their general Progenitor and Patriarch. Yet sometimes these names import all the twelve tribes, including also Levi. And sometimes, especially after the captivity of the ten tribes, these names signify the two tribes only: which more imitated Jacob's steps and virtues, than the ten.",
      "notes": [
        {
          "marker": 1,
          "text": "Four are called the greater Prophets, and twelve the less."
        },
        {
          "marker": 2,
          "text": "<i>S. Iero. Prologo. li. Reg. S. Aug. li. c. 18. c. 29. civit. Theod. Isidorus.</i>"
        },
        {
          "marker": 3,
          "text": "All these and many others were as properly Prophets as the chiefest."
        },
        {
          "marker": 4,
          "text": "<i>Epist. ad Paulin.</i>"
        },
        {
          "marker": 5,
          "text": "<i>In Osee. 1.</i>"
        },
        {
          "marker": 6,
          "text": "Of these 12, six prophesied before the captivity of the 10. tribes."
        },
        {
          "marker": 7,
          "text": "Other three also before the captivity of the two tribes, & three after the relaxation."
        },
        {
          "marker": "◦",
          "text": "Special names signifying the Kingdom of two tribes."
        },
        {
          "marker": "◦",
          "text": "Others signifying the ten tribes."
        },
        {
          "marker": "◦",
          "text": "Israel & Jacob ambiguously signify both Kingdoms."
        }
      ]
    }
  ],
  "chapters": [
    {
      "chapter": 1,
      "verses": [
        {
          "verse": 1,
          "text": "The word of our Lord, that was made to Osee the son of Beeri, in the days of Ozias, Joathan, Achaz, Ezechias, kings of Juda, and in the days <na>(a)</na> of Jeroboam the son of Joas king of Israel.",
          "notes": [
            {
              "label": "a",
              "text": "This Jeroboam King of Israel died 26. years before Ozias: whereby appeareth that Osee prophesied before Isaie: who began near the end of Ozias' reign. <i>Isa. 6.</i>"
            }
          ]
        },
        {
          "verse": 2,
          "text": "The beginning to our Lord of speaking in Osee: and our Lord said to Osee: Go, take thee a wife <na>(b)</na> of fornications, and <na>[1]</na> make children <na>(c)</na> of fornications: because the land fornicating shall fornicate from the Lord.",
          "notes": [
            {
              "label": "b",
              "text": "Take a woman that hath been a fornicatrix:"
            },
            {
              "label": "c",
              "text": "and beget children, which will also be fornicators."
            },
            {
              "label": "1",
              "text": "<i>* beget.</i>"
            }
          ]
        },
        {
          "verse": 3,
          "text": "And he went, and took Gomer the daughter of Debelaim: and she conceived, and bare him a son."
        },
        {
          "verse": 4,
          "text": "And our Lord said to him: Call his name Jezrahel: because yet a little while, and I will visit the blood <na>(d)</na> of Jezrahel upon the house of Jehu, and I will make the kingdom of the house of Israel to cease.",
          "notes": [
            {
              "label": "d",
              "text": "The issue of Jehu now reigning, solicited the 10. tribes called <i>Jezrahel</i> to idolatry, which God here saith he will revenge."
            }
          ]
        },
        {
          "verse": 5,
          "text": "And in that day I will break the bow of Israel in the valley of Jezrahel."
        },
        {
          "verse": 6,
          "text": "And she conceived yet again, and bare a daughter, and he said to him: Call her name, Without mercy: because I will add no more to have mercy on the house of Israel, but with oblivion I will forget them. <cr>[1]</cr>",
          "cross_refs": [
            {
              "text": "4. Reg. 19."
            }
          ]
        },
        {
          "verse": 7,
          "text": "And I will have mercy on the house of Juda, and will save them in the Lord their God: and I will not save them in bow and sword, and in battle, & in horses, and in horsemen."
        },
        {
          "verse": 8,
          "text": "And she weaned her that was, Without mercy. And she conceived, and bare a son."
        },
        {
          "verse": 9,
          "text": "And he said: Call his name, Not my people: because you not my people, and I will not be yours."
        },
        {
          "verse": 10,
          "text": "And the number of the children of Israel shall be as the sand of the sea, that is without measure, and shall not be numbered. And it shall be in place where it shall be said to them: Not my people you: it shall be said to them: <na>(e)</na> Children of the living God.",
          "notes": [
            {
              "label": "e",
              "text": "Among many sinners, some are the elected children of God, whom he will call to grace & repentance."
            }
          ]
        },
        {
          "verse": 11,
          "text": "And the children of Juda, and the children of Israel shall be gathered together: and they shall set to themselves, <na>(f)</na> one head, and shall ascend out of the earth: because great is the day of Jezrahel.",
          "notes": [
            {
              "label": "f",
              "text": "All the faithful have one head, our Saviour Christ."
            }
          ]
        }
      ],
      "summary": "In signification of the people's idolatry, the Prophet marrieth a fornicatrix: 4. by his children's names foresheweth their great and long captivity: 11. And afterwards their redemption together with all nations."
    },
    {
      "chapter": 2,
      "verses": [
        {
          "verse": 1,
          "text": "Say <na>(a)</na> ye to your brethren: My people: and to your sister, She that hath obtained mercy.",
          "notes": [
            {
              "label": "a",
              "text": "Ye people of Juda disdain not to call the ten tribes & the Gentiles your brethren and sisters. For God will make them also his people, as appeareth in the Gospel, more of the ten tribes than of the other Kingdom believed in Christ: & afterwards more of the Gentiles, than of the Jews."
            }
          ]
        },
        {
          "verse": 2,
          "text": "Judge your mother, judge ye: because she not my wife, and I not her husband. Let her take away fornications from her face, and her adulteries from the midst of her breasts."
        },
        {
          "verse": 3,
          "text": "Lest perhaps I strip her naked, and set her according to the day of her nativity: and I will lay her as a wilderness, and will set her as a land unpassable, and will kill her with drought."
        },
        {
          "verse": 4,
          "text": "And <na>(b)</na> I will not have mercy on her children: because they are the children of fornications:",
          "notes": [
            {
              "label": "b",
              "text": "God will not withdraw his punishments till the sinners be penitent."
            }
          ]
        },
        {
          "verse": 5,
          "text": "because their mother hath fornicated, she is confounded that conceived them: because she said: I will go after my lovers, that give me my breads, & my waters, my wool, and my flax, mine oil, & my drink."
        },
        {
          "verse": 6,
          "text": "For this behold I will hedge thy way with thorns, and I will hedge it with a wall, & she shall not find her paths."
        },
        {
          "verse": 7,
          "text": "And she shall follow her lovers, and shall not overtake them: and she shall seek them, and shall not find, and she shall say: I will go, and will return to my former husband: because it was well with me then, more than now."
        },
        {
          "verse": 8,
          "text": "And she did not know that I gave her corn, and wine, and oil, and multiplied silver unto her, & gold, which they have made to Baal."
        },
        {
          "verse": 9,
          "text": "Therefore will I return, and will take my corn in his time, and my wine in his time, and I will deliver my wool, and my flax, which covered her ignominy."
        },
        {
          "verse": 10,
          "text": "And now I will reveal her folly in the eyes of her lovers: and there shall not a man deliver her out of my hand:"
        },
        {
          "verse": 11,
          "text": "and I will make all her joy to cease, her solemnity, her new-moon, her sabbath, & all her festival times."
        },
        {
          "verse": 12,
          "text": "And I will destroy her vine, and her figtree, of which she said: These are my rewards, which my lovers have given me: and I will lay her as a forest, & the beast of the field shall eat her."
        },
        {
          "verse": 13,
          "text": "And I will visit upon her the days of Baalim, to whom she burnt incense, and was adorned with her earlet, and with her tablet, & went after her lovers, & forgot me, saith our Lord."
        },
        {
          "verse": 14,
          "text": "<na>(c)</na> For this, lo I will allure her, and will lead her into the wilderness: and I will speak to her heart.",
          "notes": [
            {
              "label": "c",
              "text": "God's mercy preventeth by his grace offered to sinners that they may convert to him if they will."
            }
          ]
        },
        {
          "verse": 15,
          "text": "And I will give her dressers of vines out of the same place, and the vale of Achor to open hope: and she shall sing there according to the days of her youth, and according to the days of her ascending out of the Land of Ægypt."
        },
        {
          "verse": 16,
          "text": "And it shall be in that day, saith our Lord: She shall call me: My husband, and she shall call me no more, Baalim."
        },
        {
          "verse": 17,
          "text": "And I will take away the names of Baalim out of her mouth, and she shall no more remember their name."
        },
        {
          "verse": 18,
          "text": "And I will make with them a league in that day, with the beast of the field, and with the fowl of the heaven, and with that, which creepeth on the earth: and bow, and sword, and battle I will destroy out of the earth: and will make them sleep confidently."
        },
        {
          "verse": 19,
          "text": "And I will despouse thee to me for ever: and I will despouse thee to me in justice, and judgement, and in mercy, and in commiserations."
        },
        {
          "verse": 20,
          "text": "And I will despouse thee to me in faith: and thou shalt know that I am the Lord."
        },
        {
          "verse": 21,
          "text": "And it shall be in that day: I will hear, saith our Lord, I will hear the heavens, and they shall hear the earth."
        },
        {
          "verse": 22,
          "text": "And the earth shall hear wheat, and wine, and oil: and these shall hear Jezrahel."
        },
        {
          "verse": 23,
          "text": "And I will sow her unto me into the earth, and <na>(d)</na> I will have mercy on her, that was without mercy.",
          "notes": [
            {
              "label": "d",
              "text": "The Apostles S. Paul. Rom. <i>9. v. 25.</i> and S. Peter. <i>ep. 1. c. 2. v. 10.</i> expound this place of the conversion of Gentiles to Christ."
            }
          ]
        },
        {
          "verse": 24,
          "text": "And I will say to Not my people: My people art thou: and it shall say: Thou art my God."
        }
      ],
      "summary": "He admonisheth the two tribes of their sins, threatening their captivity in Babylon. 1. Sheweth the aboundance of grace in the Church of Christ, and multitude of nations to be converted."
    },
    {
      "chapter": 3,
      "verses": [
        {
          "verse": 1,
          "text": "And our Lord said to me: Yet again go, love a woman beloved of her friend, and an adulteress; <na>(a)</na> as our Lord loveth the children of Israel, and they have respect to strange gods, and love the kernels of grapes.",
          "notes": [
            {
              "label": "a",
              "text": "Notwithstanding sinners forsake God, yet he offereth them new grace, never hating the persons, but their sins."
            }
          ]
        },
        {
          "verse": 2,
          "text": "And I <na>[1]</na> digged her unto me for <na>(b)</na> fifteen pieces of silver, and for a core of barley, and for half a core of barley.",
          "notes": [
            {
              "label": "b",
              "text": "The Jews not believing in Christ, but expecting his coming, and in the mean time abstaining from service of idols, receive of God temporal poor means to live, not <i>30. pieces of silver, and three cores of wheat</i>, that is, believing in the B. Trinity, and keeping the ten commandments, they might possess life everlasting, but half so much: neither wheat but barley, till near the end of the world: when they shall be converted to Christ."
            },
            {
              "label": "1",
              "text": "<i>* bought.</i>"
            }
          ]
        },
        {
          "verse": 3,
          "text": "And I said to her: Thou shalt expect me many days: thou shalt not fornicate, and thou shalt be no man's: but I also will expect thee."
        },
        {
          "verse": 4,
          "text": "Because many days shall the children of Israel sit without king, and without prince, and without sacrifice, and without altar, and without ephod, and without <na>(c)</na> theraphim.",
          "notes": [
            {
              "label": "c",
              "text": "Theraphim signifying images good or bad, being here joined with <i>King, Prince, sacrifice, altar,</i> & <i>ephod,</i> must needs signify lawful images, such as were religiously used in the temple of God. <i>3. Reg. 7. v. 36.</i>"
            }
          ]
        },
        {
          "verse": 5,
          "text": "And after this the children of Israel shall return, and shall seek the Lord their God, and David their king: and they shall dread at the Lord, and at his goodness in the last days."
        }
      ],
      "summary": "Diverse great sins of both Kingdoms, 3. are the cause of great punishments threatened, 15. yet the sins of Juda are less excusable, because they have more means to"
    },
    {
      "chapter": 4,
      "verses": [
        {
          "verse": 0,
          "text": "serve God."
        },
        {
          "verse": 1,
          "text": "Hear the word of our Lord ye <na>(a)</na> children of Israel, because there is judgement to our Lord with the inhabitants of the land: for there is no truth, and there is no mercy, and there is <na>(b)</na> no knowledge of God in the land.",
          "notes": [
            {
              "label": "a",
              "text": "Children of Israel import the whole people of the ten, & two tribes, so he speaketh to all till. <i>v. 15.</i>"
            },
            {
              "label": "b",
              "text": "Knowledge of God includeth the keeping of his commandments <i>For he that saith; he knoweth God, and keepeth not his commandments, is a liar. 1. Ioan. 2. v. 4.</i>"
            }
          ]
        },
        {
          "verse": 2,
          "text": "Cursing, and lying, and manslaughter, & theft, and adultery have overflowed, & blood hath touched blood."
        },
        {
          "verse": 3,
          "text": "For this shall the land mourn, and every one shall be weakened that dwelleth in it, in the beast of the field, and in the fowl of the heaven: yea and the fishes of the sea shall be gathered together."
        },
        {
          "verse": 4,
          "text": "But yet let not every man judge: and let not a man be rebuked: for the people are as those, that gainsay the Priest."
        },
        {
          "verse": 5,
          "text": "And thou shalt fall today, and the Prophet also shall fall with thee: in the night I made thy mother hold her peace."
        },
        {
          "verse": 6,
          "text": "My people have held their peace, because they had not knowledge: because thou hast repelled knowledge, I will repel thee, <na>(c)</na> that thou do not the function of priesthood unto me: and thou hast forgotten the law of thy God, I also will forget thy children.",
          "notes": [
            {
              "label": "c",
              "text": "Function of priests which is properly sacrifice, being taken away, all spiritual offices decay therewith."
            }
          ]
        },
        {
          "verse": 7,
          "text": "According to the multitude of them so have they sinned to me: their glory I will change into ignominy."
        },
        {
          "verse": 8,
          "text": "They shall eat <na>(d)</na> the sins of my people, and at their iniquity shall lift up their souls.",
          "notes": [
            {
              "label": "d",
              "text": "The hosts offered for sins."
            }
          ]
        },
        {
          "verse": 9,
          "text": "And as the people, so shall the Priest be: and I will visit their ways upon them, and their cogitations I will render to them."
        },
        {
          "verse": 10,
          "text": "And they shall eat and shall not be filled: they have fornicated, & have not ceased: because they have forsaken our Lord in not observing."
        },
        {
          "verse": 11,
          "text": "Fornication, & wine, & drunkenness take away the heart."
        },
        {
          "verse": 12,
          "text": "My people hath asked in their wood, & their staff hath declared unto them: for <na>(e)</na> the spirit of fornications hath deceived them, & they have fornicated from their God.",
          "notes": [
            {
              "label": "e",
              "text": "Certain sins more than others do obscure man's understanding, but spiritual fornication blindeth the heart above all other vices."
            }
          ]
        },
        {
          "verse": 13,
          "text": "Upon the heads of mountains they did sacrifice, and upon little hills they burnt incense: under the oak, and the poplar-tree, and the terebinth, because the shadow thereof was good: therefore shall your daughters fornicate, and your spouses shall be adulteresses."
        },
        {
          "verse": 14,
          "text": "I will not visit upon your daughters when they shall fornicate, and upon your spouses when they shall commit adultery: because they themselves converst with harlots, and with the effeminate they did sacrifice, and the people not understanding shall be beaten."
        },
        {
          "verse": 15,
          "text": "If thou fornicate <na>(f)</na> o Israel, at the least let not Juda offend: and enter ye not into Galgal, and go not up into Bethaven, neither swear ye: Our Lord liveth.",
          "notes": [
            {
              "label": "f",
              "text": "It was a great sin in the kingdom of Juda to commit idolatry, where they had the public true service of God in the temple, than in Israel where Jeroboam had set up calves, and forbid the people from going to Jerusalem."
            }
          ]
        },
        {
          "verse": 16,
          "text": "Because Israel hath declined as a wanton cow: now will our Lord feed them, as a lamb in latitude."
        },
        {
          "verse": 17,
          "text": "Ephraim is partaker of idols, let him alone."
        },
        {
          "verse": 18,
          "text": "Their banquet is separated, with fornication they have fornicated: the protectors thereof loved to bring ignominy."
        },
        {
          "verse": 19,
          "text": "The spirit hath bound him in his wings, and they shall be confounded at their sacrifices."
        }
      ]
    },
    {
      "chapter": 5,
      "verses": [
        {
          "verse": 1,
          "text": "Hear ye this <na>(a)</na> o Priests, and attend ye house of Israel, and you the king's house harken: because there is judgement for you, because you are become a snare to speculation, & a net spread upon Thabor.",
          "notes": [
            {
              "label": "a",
              "text": "There were no true priests in the ten tribes <i>(3. Reg. 12.)</i> but he calleth them by the title which they usurped, falsely pretending to do the offices of right Priests."
            }
          ]
        },
        {
          "verse": 2,
          "text": "And victims you have declined into the depth: & I the teacher of them all."
        },
        {
          "verse": 3,
          "text": "I know Ephraim, & Israel is not hid from me: because now hath Ephraim fornicated, Israel is contaminated."
        },
        {
          "verse": 4,
          "text": "They will not give their cogitations to return to their God, because the spirit of fornications is in the midst of them, & they have not known the Lord."
        },
        {
          "verse": 5,
          "text": "And the arrogancy of Israel shall answer in his face: and Israel and Ephraim shall fall in their iniquity, Judas also shall fall with them."
        },
        {
          "verse": 6,
          "text": "In their flocks and in their herds they shall go to seek the Lord, and shall not find: he is taken away from them."
        },
        {
          "verse": 7,
          "text": "They have prevaricated against the Lord, because they have begotten strange children: now shall a month devour them with their parts."
        },
        {
          "verse": 8,
          "text": "<na>(b)</na> Sound with the trumpet in Gabaa, & with the shalm in Rama: howl ye in Bethaven, behind thy back o Benjamin.",
          "notes": [
            {
              "label": "b",
              "text": "The captivity is here described not only in bare words but as in fact it shall happen, with tumults of war, sounding of trumpets, crying, howling &c."
            }
          ]
        },
        {
          "verse": 9,
          "text": "Ephraim shall be in desolation in the day of correction: in the tribes of Israel I have shewed faith."
        },
        {
          "verse": 10,
          "text": "The princes of Juda are become as they that take the bound: I will pour out my wrath as water upon them."
        },
        {
          "verse": 11,
          "text": "Ephraim is suffering calumny, broken in judgement: because he began to go after filthiness."
        },
        {
          "verse": 12,
          "text": "And I as it were a moth to Ephraim: & as the rot to the house of Juda."
        },
        {
          "verse": 13,
          "text": "And Ephraim saw his sickness, and Judas his band: and Ephraim went to Assur, and sent to the king revenger: and he shall not be able to heal you, neither shall he be able to loose the band from you."
        },
        {
          "verse": 14,
          "text": "Because I as it were a lioness to Ephraim, and as a lion's whelp to the house of Juda: I, I will take, and go: I will take away, and there is none that can deliver."
        },
        {
          "verse": 15,
          "text": "Going I will return to my place: until you fail and seek my face."
        }
      ],
      "summary": "The Prophet reprehendeth the Priests, and Princes of both Kingdoms, for drawing the people to idolatry: 8. denouncing captivity for the same."
    },
    {
      "chapter": 6,
      "verses": [
        {
          "verse": 1,
          "text": "In their tribulation early they will rise up to me: Come, & let us return to our Lord."
        },
        {
          "verse": 2,
          "text": "Because he <na>(a)</na> hath wounded, & will heal us: he will strike, & will cure us.",
          "notes": [
            {
              "label": "a",
              "text": "God who punisheth, is always ready to heal sinners, if they will repent."
            }
          ]
        },
        {
          "verse": 3,
          "text": "He will revive us after two days: in <na>(b)</na> the third day he will raise us up, & we shall live in his sight. We shall know, & we shall follow, that we may know our Lord. As the morning light, is his coming forth prepared, and he will come to us as a shower timely, and late to the earth.",
          "notes": [
            {
              "label": "b",
              "text": "S. Paul <i>(1. Cor. 15. v. 4.)</i> not only teaching Christ's Resurrection, but also expressly saying <i>the third day, according to the Scriptures,</i> seemeth to understand this place, where & in no other place, the day is so clearly expressed."
            }
          ]
        },
        {
          "verse": 4,
          "text": "What shall I do to thee Ephraim? What shall I do to thee Juda? Your mercy as a morning cloud, & as the dew passing away in the morning."
        },
        {
          "verse": 5,
          "text": "For this have I hewed in Prophets, I have killed them in the words of my mouth: and thy judgements shall come forth as the light:"
        },
        {
          "verse": 6,
          "text": "<cr>[1]</cr> because I would mercy, and not sacrifice: and the knowledge of God more than holocausts.",
          "cross_refs": [
            {
              "text": "Mat. 9. v. 13."
            }
          ]
        },
        {
          "verse": 7,
          "text": "But they as Adam have transgressed the covenant, there have they prevaricated against me."
        },
        {
          "verse": 8,
          "text": "Galaad a city of them that work idol, supplanted with blood."
        },
        {
          "verse": 9,
          "text": "And as it were the jaws of men that are robbers, partaker with the Priests, of them that in the way kill those that pass out of Sichem: because they have wrought wickedness."
        },
        {
          "verse": 10,
          "text": "In the house of Israel I saw an horrible thing: there the fornications of Ephraim: Israel is contaminated."
        },
        {
          "verse": 11,
          "text": "Yea and thou Juda put thee an harvest, when I shall convert the captivity of my people."
        }
      ],
      "summary": "By afflictions the people will return to God, and hope in Christ to come. 4. both the Kingdoms sinning (6. and thinking to be spared for their sacrifices, neglecting works of mercy) 7. shall be punished: 11. but at last delivered from captivity."
    },
    {
      "chapter": 7,
      "verses": [
        {
          "verse": 1,
          "text": "When <na>(a)</na> I would heal Israel, the iniquity of Ephraim was revealed, & the malice of Samaria, because they have wrought lying, & the thief hath entered in spoiling, the robber without.",
          "notes": [
            {
              "label": "a",
              "text": "God punishing all the Jews by dividing their Kingdom into two <i>(3. Reg. 12.)</i> would have cured them: but Jeroboam King of the ten tribes drew all his people into grosser sins than before, by making a schism & setting up idols to be adored for God."
            }
          ]
        },
        {
          "verse": 2,
          "text": "And lest perhaps they may say in their hearts, that I have remembered all their malice: now have their own inventions compassed them, they have been done before me."
        },
        {
          "verse": 3,
          "text": "In their malice they have rejoiced the king: and in their lies the princes."
        },
        {
          "verse": 4,
          "text": "All they committing adultery, as it were an oven heated of the baker: the city was quiet a little from the commistion of leaven, till the whole was leavened."
        },
        {
          "verse": 5,
          "text": "The day of our king, <na>(b)</na> the princes began to rage by reason of wine: he stretched out his hand with the scorners.",
          "notes": [
            {
              "label": "b",
              "text": "All the chief men of the ten tribes consented to the schism & idolatry of their new King Jeroboam."
            }
          ]
        },
        {
          "verse": 6,
          "text": "Because they have applied their heart as an oven, when he lay in wait for them: he slept all the night baking them, in the morning himself heated as a fire of flame."
        },
        {
          "verse": 7,
          "text": "All were heated as an oven, and have devoured their judges: all their kings are fallen: there is none amongst them that cryeth unto me."
        },
        {
          "verse": 8,
          "text": "Ephraim himself was <na>(c)</na> mingled in the peoples: Ephraim is become as hearth-baken-bread <na>(d)</na> that is not turned.",
          "notes": [
            {
              "label": "c",
              "text": "Became like to pagan idolaters:"
            },
            {
              "label": "d",
              "text": "and impenitent."
            }
          ]
        },
        {
          "verse": 9,
          "text": "Strangers have eaten his strength, & he knew not: yea hoar hairs also were poured out on him, & he was ignorant."
        },
        {
          "verse": 10,
          "text": "And the pride of Israel <na>(e)</na> shall be humbled in his face: neither did they return to the Lord their God, & they have not sought him in all these.",
          "notes": [
            {
              "label": "e",
              "text": "For all these sins they shall be severely punished."
            }
          ]
        },
        {
          "verse": 11,
          "text": "And Ephraim is become as a dove seduced, not having an heart: they invocated Ægypt, they went to the Assyrians."
        },
        {
          "verse": 12,
          "text": "And when they shall go forth, I will spread my net upon them: as a fowl of the heaven will I pluck them down, I will beat them according to the hearing of their assembly."
        },
        {
          "verse": 13,
          "text": "Woe to them, because they have revolted from me: they shall be wasted because they have prevaricated against me: & I redeemed them & they have spoken lies against me."
        },
        {
          "verse": 14,
          "text": "And they have not cried to me in their heart, but they howled in their chambers: upon wheat and wine they chewed the cud, they are revolted from me."
        },
        {
          "verse": 15,
          "text": "And I have taught them, and strengthened their arms: and against me they have thought malice."
        },
        {
          "verse": 16,
          "text": "They returned, that they might be without yoke: they became as a deceitful bow: their princes shall fall by the sword, for the fury of their tongue. This is their scorning in the Land of Ægypt."
        }
      ],
      "summary": "The Chaldees shall destroy the Temple. 3. But the ten tribes shall first be carried into captivity, 6. for worshiping the image of a calf."
    },
    {
      "chapter": 8,
      "verses": [
        {
          "verse": 1,
          "text": "In thy throat let there be a trumpet as an eagle upon <na>(a)</na> the house of the Lord: for that they have transgressed my covenant, and have prevaricated my law.",
          "notes": [
            {
              "label": "a",
              "text": "The temple also in Jerusalem (though not so soon) shall be destroyed."
            }
          ]
        },
        {
          "verse": 2,
          "text": "Me they shall invocate: My God, we <na>(b)</na> Israel have known thee.",
          "notes": [
            {
              "label": "b",
              "text": "But first the ten tribes of Israel for their general idolatry shall be carried into captivity by the Assyrians. <i>v. 9. & 4. Reg. 17.</i>"
            }
          ]
        },
        {
          "verse": 3,
          "text": "Israel hath cast away the good thing, the enemy shall persecute him."
        },
        {
          "verse": 4,
          "text": "They have reigned, & not of me: they have been Princes, & I knew not: their silver & their gold they made idols to themselves, that they might perish."
        },
        {
          "verse": 5,
          "text": "Thy calf is cast off o Samaria, my fury is wrath against them. How long can they not be cleansed?"
        },
        {
          "verse": 6,
          "text": "Because it-self also is of Israel: the workman made it, and it is not God: because the calf of Samaria shall be as spiders' webs."
        },
        {
          "verse": 7,
          "text": "Because they shall sow wind, & reap a whirlwind: there is no standing stalk in it, the bud shall not yield meal: & if it do yield, strangers shall eat it."
        },
        {
          "verse": 8,
          "text": "Israel is devoured: Now is he become in nations as an unclean vessel."
        },
        {
          "verse": 9,
          "text": "Because they went up to Assur, a wild ass solitary to himself: Ephraim have given gifts to lovers."
        },
        {
          "verse": 10,
          "text": "Yea and when they shall hire the nations with reward, now will I gather them together: & they shall rest a while from the burden of the king and the princes."
        },
        {
          "verse": 11,
          "text": "Because Ephraim hath multiplied altars to sin: altars are made to him unto sin."
        },
        {
          "verse": 12,
          "text": "I will write to him my manifold laws, which have been accounted as strange."
        },
        {
          "verse": 13,
          "text": "They shall offer hosts, they shall immolate flesh, and shall eat, and the Lord will not receive them: now will he remember their iniquity, and will visit their sins: they shall return into Ægypt."
        },
        {
          "verse": 14,
          "text": "And Israel hath forgotten his maker, and hath built temples: and <na>(c)</na> Judas hath multiplied fenced cities: & I will cast fire on his cities, and it shall devour the houses thereof.",
          "notes": [
            {
              "label": "c",
              "text": "The two tribes seeing the miseries of the other ten, will not prevent the like by penance, but think to escape by fortifying their cities."
            }
          ]
        }
      ]
    },
    {
      "chapter": 9,
      "verses": [
        {
          "verse": 1,
          "text": "Be not glad Israel, rejoice not as the peoples: because thou hast fornicated from thy God, thou hast loved reward above all the floors of wheat."
        },
        {
          "verse": 2,
          "text": "The floor and the winepress shall not feed them, and the wine shall lie to them."
        },
        {
          "verse": 3,
          "text": "They shall not dwell in the land of our Lord: <na>(a)</na> Ephraim is returned into Ægypt, and among the Assyrians he hath eaten the thing polluted.",
          "notes": [
            {
              "label": "a",
              "text": "Many of the Kingdom of Israel by the reason of famine and other distresses will fly into Ægypt, as both this place, and the same words <i>ch. 8. v. 13.</i> do foreshew. <i>S. Ierom. & Theodoret. v. 6.</i>"
            }
          ]
        },
        {
          "verse": 4,
          "text": "They shall not offer wine to our Lord, and they shall not please him: their sacrifices as the bread of mourners: all that shall eat it shall be contaminated: because their bread for their soul, shall not enter into the house of our Lord."
        },
        {
          "verse": 5,
          "text": "What will you do in the solemn day, in the day of the festivity of our Lord?"
        },
        {
          "verse": 6,
          "text": "For behold they are gone forth from destruction: Ægypt shall gather them together, Memphis shall bury them: their silver to be desired the nettle shall inherit, the bur in their tabernacles."
        },
        {
          "verse": 7,
          "text": "The days of visitation are come, the days are come of retributions: know <na>(b)</na> o Israel the foolish Prophet, <na>(c)</na> the mad spiritual man, for the multitude of thine iniquity, the multitude also madness.",
          "notes": [
            {
              "label": "b",
              "text": "Israel did foolishly prophesy all prosperity to themselves,"
            },
            {
              "label": "c",
              "text": "not inspired by God, but replenished with fury of madness."
            }
          ]
        },
        {
          "verse": 8,
          "text": "The watchman of Ephraim with my God: the Prophet is made a snare of ruin upon all his ways, madness in the house of his God."
        },
        {
          "verse": 9,
          "text": "They have sinned deeply, as in the days of Gabaa: <cr>[1]</cr> he will remember their iniquity, and will visit their sin.",
          "cross_refs": [
            {
              "text": "Iudic. 19. 1. Reg. 8. 4. Reg. 9."
            }
          ]
        },
        {
          "verse": 10,
          "text": "As grapes in the desert I found Israel: as the first fruits of the fig-tree in the top thereof I saw their fathers: but they have entered into Beelphegor, and are alienated into confusion, and are become abominable, as those things, which they loved."
        },
        {
          "verse": 11,
          "text": "Ephraim as a bird hath flown away, their glory from birth, and from the womb, and from conception."
        },
        {
          "verse": 12,
          "text": "But if they shall nourish up their children, I will make them without children among men: yea and woe to them, when I shall depart from them."
        },
        {
          "verse": 13,
          "text": "Ephraim, as I saw, <na>(d)</na> was Tyre founded in beauty: & Ephraim shall lead out his children to the murderer.",
          "notes": [
            {
              "label": "d",
              "text": "The kingdom of Israel was as proud and insolent as Tyre. <i>Isai. 23. Ezech. 26. 27. & 28.</i>"
            }
          ]
        },
        {
          "verse": 14,
          "text": "Give them o Lord, what wilt thou give to them? Give them a womb without children, & dry breasts."
        },
        {
          "verse": 15,
          "text": "All their wicked in Galgal, because there I hated them: for the malice of their inventions I will cast them forth out of my house: I will not add to love them, all their princes revolters."
        },
        {
          "verse": 16,
          "text": "Ephraim is strucken, their root is dried up, they shall yield no fruit. But and if they shall have issue, I will kill the best beloved things of their womb."
        },
        {
          "verse": 17,
          "text": "My God will cast them away, because they hear him not: and they shall be vagabonds in the nations."
        }
      ],
      "summary": "The ten tribes shall suffer famine: 12. be deprived of their children: 15. and made captive."
    },
    {
      "chapter": 10,
      "verses": [
        {
          "verse": 1,
          "text": "Israel a vine <na>(a)</na> thick of branches, the fruit is made equal to it: according to the multitude of his fruit he hath multiplied altars, according to the plenty of his land he hath abounded in idols.",
          "notes": [
            {
              "label": "a",
              "text": "By how much more & greater benefits Israel received of God, so much were they more ungrateful."
            }
          ]
        },
        {
          "verse": 2,
          "text": "Their heart is divided, now they shall perish: he shall break their idols, he shall destroy their altars."
        },
        {
          "verse": 3,
          "text": "Because they will now say: We have no king: for we fear not our Lord: and what shall a king do to us?"
        },
        {
          "verse": 4,
          "text": "You speak words of unprofitable vision, and you shall make a covenant: and judgement shall spring as bitterness upon the furrows of the field."
        },
        {
          "verse": 5,
          "text": "The kine of <na>(b)</na> Bethaven have the inhabitants of Samaria worshipped: Because his people mourned upon him, and his temple wardens rejoiced upon him in his glory, because it departed from him.",
          "notes": [
            {
              "label": "b",
              "text": "The house of one of their calves which Jeroboam set up for their God, otherwise called. <i>Bethel.</i>"
            }
          ]
        },
        {
          "verse": 6,
          "text": "For he also was carried unto Assur, a gift to the king Revenger: confusion shall take Ephraim, and Israel shall be confused in his own will."
        },
        {
          "verse": 7,
          "text": "Samaria hath made her king to pass as froth upon the face of water."
        },
        {
          "verse": 8,
          "text": "And the excelses of the idol the sin of Israel shall be destroyed: the bur and the thistle shall grow up over their altars: and they shall say to the mountains: Cover us, & to the little hills: Fall upon us. <cr>[1]</cr>",
          "cross_refs": [
            {
              "text": "Isa. 2. Apoc. 6."
            }
          ]
        },
        {
          "verse": 9,
          "text": "From the Days <na>(c)</na> of Gabaa, Israel hath sinned, there they stood: the battle in Gabaa upon the children of iniquity shall not apprehend them.",
          "notes": [
            {
              "label": "c",
              "text": "From the time that the tribe of Dan adored an idol which they took from Micheas ( <i>Iud. 18. v. 14.</i> which the other Israelites revenged not) they have very often either committed or suffered idolatry, which they ought to have hindered, & therefore shall at last be punished."
            }
          ]
        },
        {
          "verse": 10,
          "text": "According to my desire I will chastise them: & the peoples shall be gathered together upon them, when they shall be chastised for their two iniquities."
        },
        {
          "verse": 11,
          "text": "Ephraim an heifer taught to love threshing, & I have passed over the beauty of her neck: I will ascend upon Ephraim, Judas shall plough, Jacob shall break the furrows to himself. <cr>[1]</cr>",
          "cross_refs": [
            {
              "text": "Iere. 4."
            }
          ]
        },
        {
          "verse": 12,
          "text": "Sow to yourselves in justice, and reap in the mouth of mercy, fallow ground: but the time to seek our Lord, when he shall come that shall teach you justice."
        },
        {
          "verse": 13,
          "text": "You have ploughed impiety, you have reaped iniquity, you have eaten the fruit of lying: because thou hast trusted in thy ways, in the multitude of thy strong ones."
        },
        {
          "verse": 14,
          "text": "Atumult shall arise in thy people: and all thy munitions shall be destroyed as Salmana was destroyed by his house, that took vengeance on Baal in the day of battle, the mother being dashed in pieces upon the children. <cr>[1]</cr>",
          "cross_refs": [
            {
              "text": "Iudic. 8."
            }
          ]
        },
        {
          "verse": 15,
          "text": "So hath Bethel done to you, because of the malice of your iniquities."
        }
      ],
      "summary": "After many benefits, and advancement, much affliction shall fall upon the ten tribes, for their ingratitude towards God."
    },
    {
      "chapter": 11,
      "verses": [
        {
          "verse": 1,
          "text": "As the morning passed, hath the king of Israel passed away. Because Israel was a child, and I loved him: & <na>(a)</na> out of Ægypt I called my son. <cr>[1]</cr>",
          "cross_refs": [
            {
              "text": "Mat. 2."
            }
          ],
          "notes": [
            {
              "label": "a",
              "text": "Literally this is spoken of the people of Israel called God's son <i>(Exo. 4. v. 23.)</i> whom he delivered out of Ægypt, but mystically is verified of Christ called out of Ægypt <i>Mat. 2.</i> and is no less certain the true mystical sense, the Evangelist endued with the Holy Ghost, so interpreting, than is the literal sense of this or any other place."
            }
          ]
        },
        {
          "verse": 2,
          "text": "They called them, so they departed from their face: they immolated to Baalim, and sacrificed to idols."
        },
        {
          "verse": 3,
          "text": "And I as it were the nurse of Ephraim, carried them in mine arms: and they knew not that I cured them."
        },
        {
          "verse": 4,
          "text": "In the cords <na>(b)</na> of Adam I will draw them, in the bands of charity: and I will be to them as lifting up the yoke upon their cheeks: and I declined to him that he might eat.",
          "notes": [
            {
              "label": "b",
              "text": "God draweth men by sweet invitations, by great and many benefits agreeable to man's nature and freewill, by his love and charity: not as beasts are drawn by fear & force."
            }
          ]
        },
        {
          "verse": 5,
          "text": "He shall not return into the Land of Ægypt, and Assur he his king: because they would not convert."
        },
        {
          "verse": 6,
          "text": "The sword hath begun in his cities, and it shall consume his elect, and shall eat their heads."
        },
        {
          "verse": 7,
          "text": "And my people shall hang upon my return: but a yoke shall be put upon them together, which shall not be taken away. <cr>[1]</cr>",
          "cross_refs": [
            {
              "text": "Gen. 19."
            }
          ]
        },
        {
          "verse": 8,
          "text": "How shall I give thee Ephraim, protect thee Israel? How shall I give thee as Adama, lay thee as Seboim? My heart is turned within, my repentance is disturbed together."
        },
        {
          "verse": 9,
          "text": "I will not do the fury of my wrath: I will not return to destroy Ephraim: because I am <na>(c)</na> God, and not <na>(d)</na> man: in the midst of thee the Holy one, and I will not enter into the city.",
          "notes": [
            {
              "label": "c",
              "text": "God's property is to have mercy and to pardon."
            },
            {
              "label": "d",
              "text": "Man is prone to revenge and punish."
            }
          ]
        },
        {
          "verse": 10,
          "text": "They shall walk after our Lord, as a lion will he roar: because he will roar, and the children of the sea shall fear."
        },
        {
          "verse": 11,
          "text": "And they shall fly away as a bird out of Ægypt, and as a dove out of the Land of the Assyrians: and I will place them in their houses, saith our Lord."
        },
        {
          "verse": 12,
          "text": "Ephraim hath compassed me in denying, and the house of Israel in deceit: but Judas a witness is descended with God, and with the saints, faithful."
        }
      ],
      "summary": "The people by their sins procure their own miseries, 3. not regarding Jacob's virtues."
    },
    {
      "chapter": 12,
      "verses": [
        {
          "verse": 1,
          "text": "Ephraim <na>(a)</na> feedeth the wind, and followeth the heat: all the day he multiplieth lying and waste: and he hath made a league with the Assyrians, and he carried oil into Ægypt.",
          "notes": [
            {
              "label": "a",
              "text": "To make shew of turning to God, & to trust more in men, is as vain as to think to feed or to govern the wind."
            }
          ]
        },
        {
          "verse": 2,
          "text": "The judgement therefore of our Lord with Juda, and visitation upon Jacob: according to his ways, & according to his inventions he will render to him."
        },
        {
          "verse": 3,
          "text": "<cr>[1]</cr> In the womb he supplanted his brother: and in his strength he was directed with the Angel.",
          "cross_refs": [
            {
              "text": "Gen. 25. & 32."
            }
          ]
        },
        {
          "verse": 4,
          "text": "And he prevailed against the Angel, and was strengthened: and he wept, and besought him: in Bethel he found him, and there he spake with us."
        },
        {
          "verse": 5,
          "text": "And our Lord the God of hosts, the Lord is his memorial."
        },
        {
          "verse": 6,
          "text": "And thou shalt convert to thy God: keep mercy and judgement, & hope in thy God always."
        },
        {
          "verse": 7,
          "text": "Chanaan in his hand a deceitful balance, he hath loved calumny."
        },
        {
          "verse": 8,
          "text": "And Ephraim said: But yet I am made rich, I have found an idol to myself: all my labours shall not find me the iniquity, which I have sinned."
        },
        {
          "verse": 9,
          "text": "And I the Lord thy God out of the Land of Ægypt I will yet make thee sit in tabernacles, as in the days of festivity."
        },
        {
          "verse": 10,
          "text": "And I have spoken upon the Prophets, and I have multiplied vision, and in the hand of the Prophets I have been resembled."
        },
        {
          "verse": 11,
          "text": "If an idol in Galaad, then in vain were they in Galgal immolating with oxen: for their altars also as heaps upon the furrows of the field."
        },
        {
          "verse": 12,
          "text": "<na>(b)</na> Jacob fled into the country of Syria, <cr>[1]</cr> and Israel served for a wife, and for a wife he kept her.",
          "cross_refs": [
            {
              "text": "Gen. 28. Exo. 14."
            }
          ],
          "notes": [
            {
              "label": "b",
              "text": "The History of Jacob & his children written in Genesis & Exodus, which the Prophet here toucheth, sheweth the singular benefits of God towards this people."
            }
          ]
        },
        {
          "verse": 13,
          "text": "But by a Prophet our Lord brought Israel out of Ægypt: and by a Prophet he was preserved."
        },
        {
          "verse": 14,
          "text": "Ephraim hath provoked me to wrath in his bitterness, and his blood shall come upon him, and his reproach his Lord will restore to him."
        }
      ]
    },
    {
      "chapter": 13,
      "verses": [
        {
          "verse": 1,
          "text": "Ephraim <na>(a)</na> speaking, horror invaded Israel: & he sinned <na>(b)</na> in Baal, and died.",
          "notes": [
            {
              "label": "a",
              "text": "When Jeroboam first set up the calves to be adored, the people had horror thereof, yet consented thereto."
            },
            {
              "label": "b",
              "text": "and shortly after some added the idol of Baal <i>3. Reg. 16.</i>"
            }
          ]
        },
        {
          "verse": 2,
          "text": "And now they have added to sin: and they have made to themselves <na>(c)</na> a molten of their silver as it were the similitude of idols, the whole is the work of crafts-men: to these they say: Immolate men adoring calves.",
          "notes": [
            {
              "label": "c",
              "text": "& of other idols as this place testifieth."
            }
          ]
        },
        {
          "verse": 3,
          "text": "Therefore they shall be as a morning cloud, & as a morning dew passing away, as dust caught with a whirlwind out of the floor, and as smoke out of the chimney."
        },
        {
          "verse": 4,
          "text": "But I the Lord thy God out of the Land of Ægypt: and God beside me thou shalt not know, and there is no Saviour beside me. <cr>[1]</cr>",
          "cross_refs": [
            {
              "text": "Isa. 43."
            }
          ]
        },
        {
          "verse": 5,
          "text": "I knew thee in the desert, in the land of wilderness."
        },
        {
          "verse": 6,
          "text": "According to their pastures they were filled, and were made full: they have lifted up their heart, and have forgotten me."
        },
        {
          "verse": 7,
          "text": "And I will be unto them as a lioness, as a leopard in the way of the Assyrians."
        },
        {
          "verse": 8,
          "text": "I will meet them as a bear her young being violently taken away, and I will break in sunder the inner parts of their liver: and will consume them there as a lion, the beast of the field shall tear them."
        },
        {
          "verse": 9,
          "text": "<na>(d)</na> Perdition is thine o Israel: <na>(e)</na> only in me thy help.",
          "notes": [
            {
              "label": "d",
              "text": "Evils that happen are all of man's own procurement by his sins: whereof God is no way the author or cause:"
            },
            {
              "label": "e",
              "text": "who of his part doth all for the help of man: for whether he punish or pardon, all is to save men: so God is only cause of help and of all good, but not of evil as it is evil. He is indeed the cause of punishment, which is called <i>malum pænæ,</i> the evil of pain. <i>Amos. 3. v. 6.</i> but this for amendment during this life, and of justice after death."
            }
          ]
        },
        {
          "verse": 10,
          "text": "Where is thy king? Now especially let him save thee in all thy cities: and thy judges, of whom thou saidst: Give me kings, and princes. <cr>[1]</cr>",
          "cross_refs": [
            {
              "text": "1. Reg. 8."
            }
          ]
        },
        {
          "verse": 11,
          "text": "I will give thee a king in my fury, and will take him away in mine indignation."
        },
        {
          "verse": 12,
          "text": "The iniquity of Ephraim is bound together, his sin is hidden."
        },
        {
          "verse": 13,
          "text": "The sorrows of a woman in travail shall come to him, he a son not wise: for now he shall not stand the confraction of the children."
        },
        {
          "verse": 14,
          "text": "<na>(f)</na> Out of the hand of death I will deliver them, from death I will redeem them: I will be thy death o death, thy bite will I be o hell, consolation is hidden from mine eyes. <cr>[1]</cr>",
          "cross_refs": [
            {
              "text": "1. Cor. 15. Heb. 2. Ezec. 19."
            }
          ],
          "notes": [
            {
              "label": "f",
              "text": "This cannot be understood of temporal death, from which God will not deliver men, nor of violent death, from which he would not deliver those that were slain by the Assyrians, but necessarily of eternal death, from which the just shall be delivered."
            }
          ]
        },
        {
          "verse": 15,
          "text": "Because he shall divide between brethren: our Lord will bring a burning wind rising from the desert: and it shall dry up his veins, and shall make his fountain desolate, and he shall spoil the treasure of every vessel that is to be desired."
        }
      ],
      "summary": "For their obstinacy in idolatry, 7. greatest plagues are threatened: 10. from which none shall be able to deliver them. 14. But at last Christ coming will redeem all by his death."
    },
    {
      "chapter": 14,
      "verses": [
        {
          "verse": 1,
          "text": "Let Samaria <na>(a)</na> perish, because she hath stirred up her God to bitterness: let them perish by the sword, let their little ones be dashed, and let the women with child be cut in sunder.",
          "notes": [
            {
              "label": "a",
              "text": "Such imprecations in holy scriptures are sometimes only predictions, as <i>Psal. 68. v. 23.</i> & so here is prophesied what shall happen to the Israelites in Assyria. <i>S. Ierom.</i> sometimes are the zealous desires of saints conformable to God's justice, as <i>Psal. 149. v. 6. 7. 8. 9.</i>"
            }
          ]
        },
        {
          "verse": 2,
          "text": "Convert o Israel to our Lord thy God: because thou art fallen in thine iniquity."
        },
        {
          "verse": 3,
          "text": "<cr>[1]</cr> Take words with you, and convert to our Lord, and say to him: Take away all iniquity, and receive good: and we will render the calves of our lips.",
          "cross_refs": [
            {
              "text": "Ioel. 2. Zach. 1."
            }
          ]
        },
        {
          "verse": 4,
          "text": "Assur shall not save us, we will not mount upon horse: neither will we say any more: Our gods the work of our hands: because thou wilt have mercy on the pupil, which is in thee."
        },
        {
          "verse": 5,
          "text": "I <na>(b)</na> will heal their confractions, I will love them voluntarily: because my fury is averted from them.",
          "notes": [
            {
              "label": "b",
              "text": "When the Israelites shall convert to God, as some did when Christ came, and many will near the end of the world, then Christ will heal them."
            }
          ]
        },
        {
          "verse": 6,
          "text": "I will be as dew, Israel shall spring as the lily, and his root shall break forth as that of Libanus."
        },
        {
          "verse": 7,
          "text": "His boughs shall go, and his glory shall be as the olive-tree: and his smell as of Libanus."
        },
        {
          "verse": 8,
          "text": "They shall be converted that sit under his shadow: they shall live with wheat, and they shall spring as a vine: his memorial as the wine of Libanus."
        },
        {
          "verse": 9,
          "text": "Ephraim, what have I to do any more with idols? I will hear, and I will direct him as a verdant fir-tree: out of me thy fruit is found."
        },
        {
          "verse": 10,
          "text": "<na>(c)</na> Who is wise, and shall understand these things? Of understanding, and shall know these things? Because the ways of our Lord be right, and the just shall walk in them: but prevaricators shall fall in them.",
          "notes": [
            {
              "label": "c",
              "text": "No human wit is able to understand this (& other Prophets) yet the just shall know so much as is necessary. <i>S. Ierom in prooem. S. Aug. l. 18. c. 28. civit.</i>"
            }
          ]
        }
      ],
      "summary": "The Prophet forewarning the people of their future afflictions, 2. exhorteth them to repentance, and confession of their sins: 5. foreshewing that God will give much grace to the penitent. 10. All which mysteries only the godly wise shall understand."
    }
  ]
}
