{
  "chapter": 33,
  "annotations": [
    {
      "verse": 2,
      "title": "Came from Sinai.",
      "text": "According to the history Moyses recounteth here three benefits. First, that God gave the Law in Sinai, <i>(Exod. 20.)</i> Secondly, he cured those which were bitten with serpents near to Seir, <i>(Num. 21.)</i> Thirdly, in mount Pharan he appointed Seventy ancients to assist Moyses in judgements, <i>(Num. 11.)</i> <mn>◦</mn> But according to the Mystery, which specially is intended, S. Augustin <i>(q. 56. in Deut.)</i> saith this prophecy is not to be negligently passed over. For it evidently appeareth that this benediction pertaineth to a new people, whom Christ our Lord hath sanctified, in whose person Moyses spake and not in his own. So in this prophetical and proper sense (saith this Doctor) our Lord and Saviour cometh from <i>Sinai</i>, which is interpreted <i>tentation</i>, when he passed the tentation of his passion and death, <i>Heb. 2. v. 18.</i> Christ riseth from <i>Seir</i>, interpreted <i>hairy</i>, for that in the similitude of the flesh of sin, even of sin, he damned sin in the flesh. <i>Rom. 8. v. 3.</i> He appeareth from mount <i>Pharan</i> interpreted <i>fruitful mountain</i>, in that he giveth aboundance of grace in his Church of the new Testament, which is a city set upon a hill. <i>Mat. 5.</i>",
      "notes": [
        {
          "marker": "◦",
          "text": "The prophetical sense of these blessings is more certain, & more evident than the historical."
        }
      ]
    }
  ]
}